ehelply_logger/LogFormatter.py
ehelply_logger/Logger.py
ehelply_logger/__init__.py
tests/__init__.py
tests/test_logger.py
ehelply_logger-0.0.8.dist-info/LICENSE
ehelply_logger-0.0.8.dist-info/METADATA
ehelply_logger-0.0.8.dist-info/WHEEL
ehelply_logger-0.0.8.dist-info/top_level.txt
ehelply_logger-0.0.8.dist-info/RECORD
